build
dist
docs
examples
imf
licenses
