Metadata-Version: 2.2
Name: initial_mass_function
Version: 2025.1.20
Summary: Tools for sampling from and working with functional forms of the initial mass fuctino
Home-page: https://github.com/keflavich/imf
Author: Adam Ginsburg
Author-email: adam.g.ginsburg@gmail.com
License: BSD 3-Clause
Requires-Python: >=3.6
License-File: licenses/LICENSE.rst
Requires-Dist: astropy
Requires-Dist: numpy
Requires-Dist: scipy
Provides-Extra: test
Requires-Dist: pytest-astropy; extra == "test"
Provides-Extra: docs
Requires-Dist: sphinx-astropy; extra == "docs"
